{
  "status": "implemented",
  "summary": "Updated Himalaya sidebar help display to use ? instead of gH. Modified folder_help.lua (line 81), email_list.lua footer (line 1379), and commands/ui.lua messages (lines 11-13) for consistent help key documentation.",
  "artifacts": [
    {
      "type": "implementation",
      "path": "lua/neotex/plugins/tools/himalaya/ui/folder_help.lua",
      "summary": "Changed gH to ? in base_other help section"
    },
    {
      "type": "implementation",
      "path": "lua/neotex/plugins/tools/himalaya/ui/email_list.lua",
      "summary": "Simplified footer to simple ?:help"
    },
    {
      "type": "implementation",
      "path": "lua/neotex/plugins/tools/himalaya/commands/ui.lua",
      "summary": "Updated show_help messages to reference ? instead of gH"
    },
    {
      "type": "summary",
      "path": "specs/083_fix_himalaya_sidebar_help_display/summaries/implementation-summary-20260213.md",
      "summary": "Implementation summary with verification results"
    }
  ],
  "completion_data": {
    "completion_summary": "Fixed Himalaya sidebar help display to use ? instead of gH across all contexts. Updated folder_help.lua help section, simplified email_list.lua footer to simple ?:help, and updated all show_help() messages in commands/ui.lua. Both keybindings still work, but only ? is now documented."
  },
  "metadata": {
    "session_id": "sess_1771012924_6f6e06",
    "duration_seconds": 900,
    "agent_type": "neovim-implementation-agent",
    "delegation_depth": 1,
    "delegation_path": ["orchestrator", "implement", "neovim-implementation-agent"],
    "phases_completed": 4,
    "phases_total": 4
  },
  "next_steps": "Test changes by opening Himalaya sidebar and pressing ? to view help"
}
